{
  "VertexColorVertex": {
    "type": "vertex",
    "file": "shaders/vertex_color.vert"
  },
  "VertexColorFragment": {
    "type": "fragment", 
    "file": "shaders/vertex_color.frag"
  },
  "WireframeVertex": {
    "type": "vertex",
    "file": "shaders/wireframe.vert"
  },
  "WireframeFragment": {
    "type": "fragment",
    "file": "shaders/wireframe.frag"
  },
  "LineVertex": {
    "type": "vertex",
    "file": "shaders/line_vertex.vert"
  },
  "LineFragment": {
    "type": "fragment",
    "file": "shaders/line_fragment.frag"
  }
}